qn_scale_ble/__init__.py
qn_scale_ble/_version.py
qn_scale_ble/bluetooth.py
qn_scale_ble/body_metrics.py
qn_scale_ble/const.py
qn_scale_ble/parser.py
qn_scale_ble-0.0.1.dist-info/METADATA
qn_scale_ble-0.0.1.dist-info/WHEEL
qn_scale_ble-0.0.1.dist-info/licenses/LICENSE
qn_scale_ble-0.0.1.dist-info/RECORD
