Metadata-Version: 2.4
Name: qn_scale_ble
Version: 0.0.1
Summary: An unofficial Python package for interacting with QN-Scale smart scales using BLE. Not affiliated with the manufacturer or any of their subsidiaries.
Project-URL: Homepage, https://github.com/BHSPitMonkey/qn_scale_ble
Project-URL: Bug Tracker, https://github.com/BHSPitMonkey/qn_scale_ble/issues
Project-URL: Documentation, https://github.com/BHSPitMonkey/qn_scale_ble#readme
Project-URL: Source Code, https://github.com/BHSPitMonkey/qn_scale_ble/
Author-email: BHSPitMonkey <bhs2007@gmail.com>
License-Expression: MIT
License-File: LICENSE
Keywords: ble,bluetooth,fitness scale,health,iot,qn-scale,smart home,smart scale,weight
Classifier: Intended Audience :: Developers
Classifier: License :: OSI Approved :: MIT License
Classifier: Operating System :: OS Independent
Classifier: Programming Language :: Python :: 3
Classifier: Programming Language :: Python :: 3.10
Classifier: Programming Language :: Python :: 3.11
Classifier: Programming Language :: Python :: 3.12
Classifier: Topic :: Home Automation
Classifier: Topic :: Software Development :: Libraries :: Python Modules
Requires-Python: >=3.10
Requires-Dist: bleak
Requires-Dist: bleak-retry-connector
